{
  "id": "synthetic_40c_120q_random_s391905418",
  "type": "generated",
  "name": "Synthetic Random",
  "description": "Random instance generated using seed 391905418, with customer demands ranging from 5 to 30.",
  "depot": {
    "x": 50.0,
    "y": 50.0
  },
  "customers": [
    {
      "id": 1,
      "location": {
        "x": 37.71272061552218,
        "y": 46.60009394437851
      },
      "demand": 21,
      "ready_time": null,
      "due_time": null,
      "service_time": 0
    },
    {
      "id": 2,
      "location": {
        "x": 25.951896599254653,
        "y": 32.9094205181907
      },
      "demand": 20,
      "ready_time": null,
      "due_time": null,
      "service_time": 0
    },
    {
      "id": 3,
      "location": {
        "x": 9.365412412435015,
        "y": 22.839699324882112
      },
      "demand": 7,
      "ready_time": null,
      "due_time": null,
      "service_time": 0
    },
    {
      "id": 4,
      "location": {
        "x": 61.127450088629686,
        "y": 20.918225011051362
      },
      "demand": 22,
      "ready_time": null,
      "due_time": null,
      "service_time": 0
    },
    {
      "id": 5,
      "location": {
        "x": 51.753913908633585,
        "y": 72.88774405002259
      },
      "demand": 25,
      "ready_time": null,
      "due_time": null,
      "service_time": 0
    },
    {
      "id": 6,
      "location": {
        "x": 46.02741084662316,
        "y": 73.08790878613338
      },
      "demand": 22,
      "ready_time": null,
      "due_time": null,
      "service_time": 0
    },
    {
      "id": 7,
      "location": {
        "x": 79.29236376678824,
        "y": 51.73220979933427
      },
      "demand": 25,
      "ready_time": null,
      "due_time": null,
      "service_time": 0
    },
    {
      "id": 8,
      "location": {
        "x": 98.0356781257449,
        "y": 43.45852326140841
      },
      "demand": 21,
      "ready_time": null,
      "due_time": null,
      "service_time": 0
    },
    {
      "id": 9,
      "location": {
        "x": 97.26652426761322,
        "y": 8.316990355091258
      },
      "demand": 8,
      "ready_time": null,
      "due_time": null,
      "service_time": 0
    },
    {
      "id": 10,
      "location": {
        "x": 55.95679450344752,
        "y": 22.919127812711015
      },
      "demand": 22,
      "ready_time": null,
      "due_time": null,
      "service_time": 0
    },
    {
      "id": 11,
      "location": {
        "x": 28.034862461992482,
        "y": 52.03890184284031
      },
      "demand": 24,
      "ready_time": null,
      "due_time": null,
      "service_time": 0
    },
    {
      "id": 12,
      "location": {
        "x": 5.897944970567326,
        "y": 59.05409842259958
      },
      "demand": 27,
      "ready_time": null,
      "due_time": null,
      "service_time": 0
    },
    {
      "id": 13,
      "location": {
        "x": 99.90177253955956,
        "y": 11.828026475733234
      },
      "demand": 27,
      "ready_time": null,
      "due_time": null,
      "service_time": 0
    },
    {
      "id": 14,
      "location": {
        "x": 86.90225779108411,
        "y": 85.56998855630641
      },
      "demand": 8,
      "ready_time": null,
      "due_time": null,
      "service_time": 0
    },
    {
      "id": 15,
      "location": {
        "x": 9.07132363017512,
        "y": 40.77781462674183
      },
      "demand": 14,
      "ready_time": null,
      "due_time": null,
      "service_time": 0
    },
    {
      "id": 16,
      "location": {
        "x": 38.08436751482829,
        "y": 14.997305159405872
      },
      "demand": 10,
      "ready_time": null,
      "due_time": null,
      "service_time": 0
    },
    {
      "id": 17,
      "location": {
        "x": 93.84102483444958,
        "y": 10.329294528145304
      },
      "demand": 26,
      "ready_time": null,
      "due_time": null,
      "service_time": 0
    },
    {
      "id": 18,
      "location": {
        "x": 74.24533875931581,
        "y": 75.79258085696154
      },
      "demand": 26,
      "ready_time": null,
      "due_time": null,
      "service_time": 0
    },
    {
      "id": 19,
      "location": {
        "x": 76.33838700059957,
        "y": 71.0106066433652
      },
      "demand": 26,
      "ready_time": null,
      "due_time": null,
      "service_time": 0
    },
    {
      "id": 20,
      "location": {
        "x": 20.242829013914964,
        "y": 24.776906911195507
      },
      "demand": 22,
      "ready_time": null,
      "due_time": null,
      "service_time": 0
    },
    {
      "id": 21,
      "location": {
        "x": 27.946063029665957,
        "y": 45.469199764020395
      },
      "demand": 26,
      "ready_time": null,
      "due_time": null,
      "service_time": 0
    },
    {
      "id": 22,
      "location": {
        "x": 48.637534931041095,
        "y": 84.07697755303788
      },
      "demand": 15,
      "ready_time": null,
      "due_time": null,
      "service_time": 0
    },
    {
      "id": 23,
      "location": {
        "x": 69.06101971799754,
        "y": 24.987779928115117
      },
      "demand": 24,
      "ready_time": null,
      "due_time": null,
      "service_time": 0
    },
    {
      "id": 24,
      "location": {
        "x": 38.721684891239775,
        "y": 73.39656167643929
      },
      "demand": 20,
      "ready_time": null,
      "due_time": null,
      "service_time": 0
    },
    {
      "id": 25,
      "location": {
        "x": 46.84242525212725,
        "y": 35.12806767859249
      },
      "demand": 24,
      "ready_time": null,
      "due_time": null,
      "service_time": 0
    },
    {
      "id": 26,
      "location": {
        "x": 34.76938486118867,
        "y": 20.48436424518254
      },
      "demand": 30,
      "ready_time": null,
      "due_time": null,
      "service_time": 0
    },
    {
      "id": 27,
      "location": {
        "x": 38.834983687798875,
        "y": 92.64438521118407
      },
      "demand": 25,
      "ready_time": null,
      "due_time": null,
      "service_time": 0
    },
    {
      "id": 28,
      "location": {
        "x": 24.592306802238873,
        "y": 25.006750100916676
      },
      "demand": 19,
      "ready_time": null,
      "due_time": null,
      "service_time": 0
    },
    {
      "id": 29,
      "location": {
        "x": 82.90073471127734,
        "y": 35.043096894876335
      },
      "demand": 12,
      "ready_time": null,
      "due_time": null,
      "service_time": 0
    },
    {
      "id": 30,
      "location": {
        "x": 56.23397598914094,
        "y": 95.27400326261531
      },
      "demand": 26,
      "ready_time": null,
      "due_time": null,
      "service_time": 0
    },
    {
      "id": 31,
      "location": {
        "x": 27.61786743408532,
        "y": 72.72643683568295
      },
      "demand": 22,
      "ready_time": null,
      "due_time": null,
      "service_time": 0
    },
    {
      "id": 32,
      "location": {
        "x": 22.23903448690433,
        "y": 89.14047646764529
      },
      "demand": 8,
      "ready_time": null,
      "due_time": null,
      "service_time": 0
    },
    {
      "id": 33,
      "location": {
        "x": 28.71045634763122,
        "y": 39.74629834381444
      },
      "demand": 14,
      "ready_time": null,
      "due_time": null,
      "service_time": 0
    },
    {
      "id": 34,
      "location": {
        "x": 96.93140566597084,
        "y": 23.28557869177883
      },
      "demand": 13,
      "ready_time": null,
      "due_time": null,
      "service_time": 0
    },
    {
      "id": 35,
      "location": {
        "x": 97.05325791304391,
        "y": 13.66123538303209
      },
      "demand": 25,
      "ready_time": null,
      "due_time": null,
      "service_time": 0
    },
    {
      "id": 36,
      "location": {
        "x": 20.886760545706863,
        "y": 54.1957964560189
      },
      "demand": 5,
      "ready_time": null,
      "due_time": null,
      "service_time": 0
    },
    {
      "id": 37,
      "location": {
        "x": 25.960594347109932,
        "y": 80.58820137824635
      },
      "demand": 27,
      "ready_time": null,
      "due_time": null,
      "service_time": 0
    },
    {
      "id": 38,
      "location": {
        "x": 73.05765501464133,
        "y": 36.5418619630537
      },
      "demand": 19,
      "ready_time": null,
      "due_time": null,
      "service_time": 0
    },
    {
      "id": 39,
      "location": {
        "x": 91.72971010850326,
        "y": 11.155566432258412
      },
      "demand": 18,
      "ready_time": null,
      "due_time": null,
      "service_time": 0
    },
    {
      "id": 40,
      "location": {
        "x": 84.92532757752547,
        "y": 44.825768995633986
      },
      "demand": 26,
      "ready_time": null,
      "due_time": null,
      "service_time": 0
    }
  ],
  "vehicle_capacity": 120,
  "max_vehicles": null,
  "distance_matrix": null,
  "seed": 391905418,
  "num_clusters": null
}